bruce_li_tc/__init__.py
bruce_li_tc/_version.py
bruce_li_tc/bruce_autostart/__init__.py
bruce_li_tc/bruce_autostart/b_autostart.py
bruce_li_tc/bruce_autostart/b_windows_service.py
bruce_li_tc/bruce_c/B_CTypesHelper.py
bruce_li_tc/bruce_c/__init__.py
bruce_li_tc/bruce_crawler/__init__.py
bruce_li_tc/bruce_crawler/dy_crawler/__init__.py
bruce_li_tc/bruce_crawler/dy_crawler/dy_core.py
bruce_li_tc/bruce_crawler/dy_crawler/dy_sx.py
bruce_li_tc/bruce_crawler/spider_guard/__init__.py
bruce_li_tc/bruce_crawler/spider_guard/default_words.py
bruce_li_tc/bruce_crawler/spider_guard/detector.py
bruce_li_tc/bruce_crawler/xhs_crawler/__init__.py
bruce_li_tc/bruce_crawler/xhs_crawler/xhs_core.py
bruce_li_tc/bruce_crawler/xhs_crawler/xhs_utils.py
bruce_li_tc/bruce_design_patterns/B_behavioral.py
bruce_li_tc/bruce_design_patterns/B_creational.py
bruce_li_tc/bruce_design_patterns/B_structural.py
bruce_li_tc/bruce_design_patterns/__init__.py
bruce_li_tc/bruce_gui_tool/__init__.py
bruce_li_tc/bruce_gui_tool/b_windows_qt_autostart.py
bruce_li_tc/bruce_gui_tool/pyinstaller_gui/__init__.py
bruce_li_tc/bruce_gui_tool/pyinstaller_gui/core.py
bruce_li_tc/bruce_gui_tool/pyinstaller_gui/gui.py
bruce_li_tc/bruce_gui_tool/pyinstaller_gui/utils.py
bruce_li_tc/bruce_gui_tool/pyinstaller_gui/worker.py
bruce_li_tc/bruce_network/B_NetworkUtils.py
bruce_li_tc/bruce_network/__init__.py
bruce_li_tc/bruce_pyinstaller/B_pyinstaller.py
bruce_li_tc/bruce_pyinstaller/__init__.py
bruce_li_tc/bruce_read_asyncio/__init__.py
bruce_li_tc/bruce_read_asyncio/b_future.py
bruce_li_tc/bruce_subprocess/__init__.py
bruce_li_tc/bruce_subprocess/async_controller.py
bruce_li_tc/bruce_subprocess/encoding_utils.py
bruce_li_tc/bruce_subprocess/sync_controller.py
bruce_li_tc/bruce_tools/B_HttpClient.py
bruce_li_tc/bruce_tools/B_KeyConverter.py
bruce_li_tc/bruce_tools/B_LogManager.py
bruce_li_tc/bruce_tools/B_MySQLHelper.py
bruce_li_tc/bruce_tools/B_RandomTool.py
bruce_li_tc/bruce_tools/B_RedisHelper.py
bruce_li_tc-0.7.4.dist-info/METADATA
bruce_li_tc-0.7.4.dist-info/WHEEL
bruce_li_tc-0.7.4.dist-info/top_level.txt
bruce_li_tc-0.7.4.dist-info/RECORD
