Metadata-Version: 2.4
Name: bruce-li-tc
Version: 0.7.4
Summary: Advanced Python utilities for time and data processing
Author-email: Bruce Li <bruce.li@example.com>
License: MIT
Requires-Python: >=3.8
Requires-Dist: requests==2.32.4
Requires-Dist: pytz==2025.2
Requires-Dist: python-dateutil==2.9.0
Requires-Dist: loguru==0.7.3
Requires-Dist: pymysql==1.1.1
Requires-Dist: redis==6.2.0
Requires-Dist: datetime==5.5
Requires-Dist: dbutils==3.1.1
Requires-Dist: pyqt6==6.9.1
Requires-Dist: playwright==1.54.0
Requires-Dist: PyAutoGUI==0.9.54
Requires-Dist: uiautomation==2.0.29
Requires-Dist: pillow==11.3.0
Requires-Dist: opencv-python==4.12.0.88
